README.md
setup.py
threewfund/__init__.py
threewfund/datatool.py
zhu_3w.egg-info/PKG-INFO
zhu_3w.egg-info/SOURCES.txt
zhu_3w.egg-info/dependency_links.txt
zhu_3w.egg-info/top_level.txt