Metadata-Version: 2.1
Name: zhu-3w
Version: 1.0.17
Summary: to find and copy data from the web
Author: Kenneth
Author-email: sf.zhu@foxmail.com
License: Apache 2.0
Keywords: threewfund
Classifier: Development Status :: 3 - Alpha
Classifier: Intended Audience :: Developers
Classifier: Programming Language :: Python :: 3
Classifier: Programming Language :: Python :: 3.7
Classifier: Programming Language :: Python :: 3.8
Classifier: Programming Language :: Python :: 3.9
Classifier: Programming Language :: Python :: 3.10
Classifier: Programming Language :: Python :: 3 :: Only
Classifier: License :: OSI Approved :: MIT License
Classifier: Operating System :: OS Independent
